[{"contractYm":"202603","contractDay":"30","price":72000,"deposit":0,"monthlyRent":0,"area":84.5442,"areaPyeong":25.6,"floor":7,"dealType":"매매"},{"contractYm":"202603","contractDay":"28","price":59000,"deposit":0,"monthlyRent":0,"area":59.9912,"areaPyeong":18.1,"floor":13,"dealType":"매매"},{"contractYm":"202603","contractDay":"23","price":0,"deposit":41400,"monthlyRent":0,"area":84.52,"areaPyeong":25.6,"floor":21,"dealType":"전세"},{"contractYm":"202603","contractDay":"21","price":54300,"deposit":0,"monthlyRent":0,"area":59.9912,"areaPyeong":18.1,"floor":2,"dealType":"중개거래"},{"contractYm":"202603","contractDay":"21","price":0,"deposit":36750,"monthlyRent":0,"area":59.9912,"areaPyeong":18.1,"floor":8,"dealType":"전세"},{"contractYm":"202603","contractDay":"18","price":72000,"deposit":0,"monthlyRent":0,"area":84.5413,"areaPyeong":25.6,"floor":14,"dealType":"매매"},{"contractYm":"202603","contractDay":"18","price":56000,"deposit":0,"monthlyRent":0,"area":60.3768,"areaPyeong":18.3,"floor":2,"dealType":"매매"},{"contractYm":"202603","contractDay":"18","price":0,"deposit":22000,"monthlyRent":0,"area":59.9912,"areaPyeong":18.1,"floor":2,"dealType":"전세"},{"contractYm":"202603","contractDay":"18","price":60800,"deposit":0,"monthlyRent":0,"area":59.9912,"areaPyeong":18.1,"floor":27,"dealType":"매매"},{"contractYm":"202603","contractDay":"14","price":0,"deposit":40000,"monthlyRent":0,"area":84.52,"areaPyeong":25.6,"floor":13,"dealType":"전세"},{"contractYm":"202603","contractDay":"07","price":0,"deposit":30450,"monthlyRent":0,"area":59.9912,"areaPyeong":18.1,"floor":15,"dealType":"전세"},{"contractYm":"202603","contractDay":"04","price":0,"deposit":31050,"monthlyRent":0,"area":59.9912,"areaPyeong":18.1,"floor":20,"dealType":"전세"},{"contractYm":"202603","contractDay":"04","price":0,"deposit":36000,"monthlyRent":0,"area":59.9912,"areaPyeong":18.1,"floor":19,"dealType":"전세"},{"contractYm":"202603","contractDay":"02","price":0,"deposit":35000,"monthlyRent":0,"area":60.3768,"areaPyeong":18.3,"floor":13,"dealType":"전세"},{"contractYm":"202602","contractDay":"28","price":59900,"deposit":0,"monthlyRent":0,"area":59.9912,"areaPyeong":18.1,"floor":19,"dealType":"중개거래"},{"contractYm":"202602","contractDay":"21","price":76400,"deposit":0,"monthlyRent":0,"area":84.52,"areaPyeong":25.6,"floor":18,"dealType":"중개거래"},{"contractYm":"202602","contractDay":"08","price":59800,"deposit":0,"monthlyRent":0,"area":60.3768,"areaPyeong":18.3,"floor":11,"dealType":"중개거래"},{"contractYm":"202602","contractDay":"07","price":58250,"deposit":0,"monthlyRent":0,"area":59.9912,"areaPyeong":18.1,"floor":5,"dealType":"중개거래"},{"contractYm":"202602","contractDay":"06","price":71800,"deposit":0,"monthlyRent":0,"area":84.5413,"areaPyeong":25.6,"floor":24,"dealType":"중개거래"},{"contractYm":"202602","contractDay":"06","price":59800,"deposit":0,"monthlyRent":0,"area":59.9912,"areaPyeong":18.1,"floor":20,"dealType":"중개거래"},{"contractYm":"202602","contractDay":"02","price":59700,"deposit":0,"monthlyRent":0,"area":59.9912,"areaPyeong":18.1,"floor":5,"dealType":"중개거래"},{"contractYm":"202601","contractDay":"31","price":57500,"deposit":0,"monthlyRent":0,"area":59.9912,"areaPyeong":18.1,"floor":12,"dealType":"중개거래"},{"contractYm":"202601","contractDay":"30","price":59500,"deposit":0,"monthlyRent":0,"area":60.3768,"areaPyeong":18.3,"floor":15,"dealType":"중개거래"},{"contractYm":"202601","contractDay":"30","price":52000,"deposit":0,"monthlyRent":0,"area":59.9912,"areaPyeong":18.1,"floor":2,"dealType":"중개거래"},{"contractYm":"202601","contractDay":"25","price":56500,"deposit":0,"monthlyRent":0,"area":59.9912,"areaPyeong":18.1,"floor":7,"dealType":"중개거래"},{"contractYm":"202601","contractDay":"19","price":56000,"deposit":0,"monthlyRent":0,"area":59.9912,"areaPyeong":18.1,"floor":6,"dealType":"중개거래"},{"contractYm":"202601","contractDay":"14","price":60800,"deposit":0,"monthlyRent":0,"area":59.9912,"areaPyeong":18.1,"floor":18,"dealType":"중개거래"},{"contractYm":"202601","contractDay":"14","price":56500,"deposit":0,"monthlyRent":0,"area":59.9912,"areaPyeong":18.1,"floor":9,"dealType":"중개거래"},{"contractYm":"202601","contractDay":"12","price":70000,"deposit":0,"monthlyRent":0,"area":84.5413,"areaPyeong":25.6,"floor":20,"dealType":"중개거래"},{"contractYm":"202601","contractDay":"10","price":59500,"deposit":0,"monthlyRent":0,"area":59.9912,"areaPyeong":18.1,"floor":24,"dealType":"중개거래"},{"contractYm":"202601","contractDay":"05","price":72000,"deposit":0,"monthlyRent":0,"area":84.5442,"areaPyeong":25.6,"floor":13,"dealType":"중개거래"},{"contractYm":"202512","contractDay":"27","price":72000,"deposit":0,"monthlyRent":0,"area":84.5442,"areaPyeong":25.6,"floor":22,"dealType":"중개거래"},{"contractYm":"202512","contractDay":"26","price":58900,"deposit":0,"monthlyRent":0,"area":60.3768,"areaPyeong":18.3,"floor":12,"dealType":"중개거래"},{"contractYm":"202512","contractDay":"19","price":74800,"deposit":0,"monthlyRent":0,"area":84.52,"areaPyeong":25.6,"floor":25,"dealType":"중개거래"},{"contractYm":"202512","contractDay":"15","price":56800,"deposit":0,"monthlyRent":0,"area":59.9912,"areaPyeong":18.1,"floor":6,"dealType":"중개거래"},{"contractYm":"202512","contractDay":"09","price":59000,"deposit":0,"monthlyRent":0,"area":59.9912,"areaPyeong":18.1,"floor":18,"dealType":"중개거래"},{"contractYm":"202512","contractDay":"02","price":57000,"deposit":0,"monthlyRent":0,"area":59.9912,"areaPyeong":18.1,"floor":19,"dealType":"중개거래"},{"contractYm":"202511","contractDay":"29","price":71000,"deposit":0,"monthlyRent":0,"area":84.5442,"areaPyeong":25.6,"floor":23,"dealType":"중개거래"},{"contractYm":"202511","contractDay":"28","price":58400,"deposit":0,"monthlyRent":0,"area":59.9912,"areaPyeong":18.1,"floor":21,"dealType":"중개거래"},{"contractYm":"202511","contractDay":"21","price":59100,"deposit":0,"monthlyRent":0,"area":59.9912,"areaPyeong":18.1,"floor":23,"dealType":"중개거래"},{"contractYm":"202511","contractDay":"19","price":59700,"deposit":0,"monthlyRent":0,"area":59.9912,"areaPyeong":18.1,"floor":17,"dealType":"중개거래"},{"contractYm":"202511","contractDay":"15","price":73000,"deposit":0,"monthlyRent":0,"area":84.52,"areaPyeong":25.6,"floor":5,"dealType":"중개거래"},{"contractYm":"202511","contractDay":"13","price":69900,"deposit":0,"monthlyRent":0,"area":84.5442,"areaPyeong":25.6,"floor":6,"dealType":"중개거래"},{"contractYm":"202511","contractDay":"08","price":59500,"deposit":0,"monthlyRent":0,"area":59.9912,"areaPyeong":18.1,"floor":20,"dealType":"중개거래"},{"contractYm":"202511","contractDay":"07","price":59500,"deposit":0,"monthlyRent":0,"area":59.9912,"areaPyeong":18.1,"floor":26,"dealType":"중개거래"},{"contractYm":"202511","contractDay":"05","price":51600,"deposit":0,"monthlyRent":0,"area":60.3768,"areaPyeong":18.3,"floor":2,"dealType":"중개거래"},{"contractYm":"202511","contractDay":"04","price":73000,"deposit":0,"monthlyRent":0,"area":84.52,"areaPyeong":25.6,"floor":26,"dealType":"중개거래"},{"contractYm":"202511","contractDay":"01","price":69500,"deposit":0,"monthlyRent":0,"area":84.5442,"areaPyeong":25.6,"floor":3,"dealType":"중개거래"},{"contractYm":"202511","contractDay":"01","price":56800,"deposit":0,"monthlyRent":0,"area":59.9912,"areaPyeong":18.1,"floor":8,"dealType":"중개거래"},{"contractYm":"202510","contractDay":"29","price":56000,"deposit":0,"monthlyRent":0,"area":59.9912,"areaPyeong":18.1,"floor":18,"dealType":"중개거래"},{"contractYm":"202510","contractDay":"28","price":57400,"deposit":0,"monthlyRent":0,"area":59.9912,"areaPyeong":18.1,"floor":10,"dealType":"중개거래"},{"contractYm":"202510","contractDay":"25","price":59300,"deposit":0,"monthlyRent":0,"area":59.9912,"areaPyeong":18.1,"floor":21,"dealType":"중개거래"},{"contractYm":"202510","contractDay":"25","price":59000,"deposit":0,"monthlyRent":0,"area":59.9912,"areaPyeong":18.1,"floor":11,"dealType":"중개거래"},{"contractYm":"202510","contractDay":"24","price":57900,"deposit":0,"monthlyRent":0,"area":60.3768,"areaPyeong":18.3,"floor":5,"dealType":"중개거래"},{"contractYm":"202510","contractDay":"20","price":55000,"deposit":0,"monthlyRent":0,"area":59.9912,"areaPyeong":18.1,"floor":22,"dealType":"중개거래"},{"contractYm":"202510","contractDay":"17","price":58700,"deposit":0,"monthlyRent":0,"area":59.9912,"areaPyeong":18.1,"floor":25,"dealType":"중개거래"},{"contractYm":"202510","contractDay":"16","price":69200,"deposit":0,"monthlyRent":0,"area":84.5413,"areaPyeong":25.6,"floor":8,"dealType":"중개거래"},{"contractYm":"202510","contractDay":"15","price":56500,"deposit":0,"monthlyRent":0,"area":59.9912,"areaPyeong":18.1,"floor":21,"dealType":"중개거래"},{"contractYm":"202510","contractDay":"11","price":55500,"deposit":0,"monthlyRent":0,"area":59.9912,"areaPyeong":18.1,"floor":10,"dealType":"중개거래"},{"contractYm":"202510","contractDay":"04","price":71500,"deposit":0,"monthlyRent":0,"area":84.52,"areaPyeong":25.6,"floor":11,"dealType":"중개거래"},{"contractYm":"202509","contractDay":"24","price":70500,"deposit":0,"monthlyRent":0,"area":84.5413,"areaPyeong":25.6,"floor":20,"dealType":"중개거래"},{"contractYm":"202509","contractDay":"20","price":58300,"deposit":0,"monthlyRent":0,"area":60.3768,"areaPyeong":18.3,"floor":7,"dealType":"중개거래"},{"contractYm":"202509","contractDay":"19","price":48000,"deposit":0,"monthlyRent":0,"area":59.9912,"areaPyeong":18.1,"floor":11,"dealType":"중개거래"},{"contractYm":"202509","contractDay":"16","price":58300,"deposit":0,"monthlyRent":0,"area":59.9912,"areaPyeong":18.1,"floor":11,"dealType":"중개거래"},{"contractYm":"202509","contractDay":"12","price":55000,"deposit":0,"monthlyRent":0,"area":59.9912,"areaPyeong":18.1,"floor":23,"dealType":"중개거래"},{"contractYm":"202509","contractDay":"06","price":58300,"deposit":0,"monthlyRent":0,"area":60.3768,"areaPyeong":18.3,"floor":8,"dealType":"중개거래"},{"contractYm":"202508","contractDay":"19","price":55000,"deposit":0,"monthlyRent":0,"area":59.9912,"areaPyeong":18.1,"floor":3,"dealType":"중개거래"},{"contractYm":"202508","contractDay":"12","price":57000,"deposit":0,"monthlyRent":0,"area":59.9912,"areaPyeong":18.1,"floor":6,"dealType":"중개거래"},{"contractYm":"202507","contractDay":"19","price":71000,"deposit":0,"monthlyRent":0,"area":84.52,"areaPyeong":25.6,"floor":16,"dealType":"중개거래"},{"contractYm":"202507","contractDay":"07","price":56800,"deposit":0,"monthlyRent":0,"area":59.9912,"areaPyeong":18.1,"floor":7,"dealType":"중개거래"},{"contractYm":"202506","contractDay":"26","price":56800,"deposit":0,"monthlyRent":0,"area":59.9912,"areaPyeong":18.1,"floor":7,"dealType":"중개거래"},{"contractYm":"202506","contractDay":"26","price":56500,"deposit":0,"monthlyRent":0,"area":59.9912,"areaPyeong":18.1,"floor":7,"dealType":"중개거래"},{"contractYm":"202506","contractDay":"24","price":57000,"deposit":0,"monthlyRent":0,"area":60.3768,"areaPyeong":18.3,"floor":11,"dealType":"중개거래"},{"contractYm":"202506","contractDay":"14","price":56500,"deposit":0,"monthlyRent":0,"area":59.9912,"areaPyeong":18.1,"floor":8,"dealType":"중개거래"},{"contractYm":"202506","contractDay":"11","price":68000,"deposit":0,"monthlyRent":0,"area":84.52,"areaPyeong":25.6,"floor":1,"dealType":"중개거래"},{"contractYm":"202506","contractDay":"07","price":55700,"deposit":0,"monthlyRent":0,"area":59.9912,"areaPyeong":18.1,"floor":13,"dealType":"중개거래"},{"contractYm":"202506","contractDay":"07","price":54500,"deposit":0,"monthlyRent":0,"area":59.9912,"areaPyeong":18.1,"floor":20,"dealType":"중개거래"},{"contractYm":"202505","contractDay":"31","price":56000,"deposit":0,"monthlyRent":0,"area":59.9912,"areaPyeong":18.1,"floor":23,"dealType":"중개거래"},{"contractYm":"202505","contractDay":"20","price":70700,"deposit":0,"monthlyRent":0,"area":84.52,"areaPyeong":25.6,"floor":20,"dealType":"중개거래"},{"contractYm":"202503","contractDay":"22","price":56000,"deposit":0,"monthlyRent":0,"area":60.3768,"areaPyeong":18.3,"floor":7,"dealType":"중개거래"},{"contractYm":"202503","contractDay":"21","price":56500,"deposit":0,"monthlyRent":0,"area":60.3768,"areaPyeong":18.3,"floor":10,"dealType":"중개거래"},{"contractYm":"202503","contractDay":"21","price":53000,"deposit":0,"monthlyRent":0,"area":59.9912,"areaPyeong":18.1,"floor":27,"dealType":"중개거래"},{"contractYm":"202503","contractDay":"15","price":55700,"deposit":0,"monthlyRent":0,"area":59.9912,"areaPyeong":18.1,"floor":13,"dealType":"중개거래"},{"contractYm":"202503","contractDay":"11","price":54600,"deposit":0,"monthlyRent":0,"area":59.9912,"areaPyeong":18.1,"floor":25,"dealType":"중개거래"},{"contractYm":"202503","contractDay":"08","price":72000,"deposit":0,"monthlyRent":0,"area":84.5413,"areaPyeong":25.6,"floor":5,"dealType":"중개거래"},{"contractYm":"202503","contractDay":"08","price":55500,"deposit":0,"monthlyRent":0,"area":59.9912,"areaPyeong":18.1,"floor":8,"dealType":"중개거래"},{"contractYm":"202503","contractDay":"08","price":55000,"deposit":0,"monthlyRent":0,"area":59.9912,"areaPyeong":18.1,"floor":23,"dealType":"중개거래"},{"contractYm":"202502","contractDay":"24","price":54250,"deposit":0,"monthlyRent":0,"area":59.9912,"areaPyeong":18.1,"floor":15,"dealType":"중개거래"},{"contractYm":"202502","contractDay":"11","price":53000,"deposit":0,"monthlyRent":0,"area":59.9912,"areaPyeong":18.1,"floor":24,"dealType":"중개거래"},{"contractYm":"202502","contractDay":"07","price":55000,"deposit":0,"monthlyRent":0,"area":59.9912,"areaPyeong":18.1,"floor":22,"dealType":"중개거래"},{"contractYm":"202501","contractDay":"31","price":55200,"deposit":0,"monthlyRent":0,"area":59.9912,"areaPyeong":18.1,"floor":27,"dealType":"중개거래"},{"contractYm":"202412","contractDay":"09","price":62000,"deposit":0,"monthlyRent":0,"area":84.5442,"areaPyeong":25.6,"floor":8,"dealType":"직거래"},{"contractYm":"202412","contractDay":"05","price":53500,"deposit":0,"monthlyRent":0,"area":59.9912,"areaPyeong":18.1,"floor":16,"dealType":"중개거래"},{"contractYm":"202411","contractDay":"19","price":50000,"deposit":0,"monthlyRent":0,"area":60.3768,"areaPyeong":18.3,"floor":7,"dealType":"중개거래"},{"contractYm":"202411","contractDay":"19","price":50800,"deposit":0,"monthlyRent":0,"area":59.9912,"areaPyeong":18.1,"floor":3,"dealType":"중개거래"},{"contractYm":"202410","contractDay":"29","price":73000,"deposit":0,"monthlyRent":0,"area":84.5442,"areaPyeong":25.6,"floor":21,"dealType":"중개거래"},{"contractYm":"202410","contractDay":"29","price":57000,"deposit":0,"monthlyRent":0,"area":60.3768,"areaPyeong":18.3,"floor":15,"dealType":"중개거래"},{"contractYm":"202410","contractDay":"11","price":59000,"deposit":0,"monthlyRent":0,"area":59.9912,"areaPyeong":18.1,"floor":25,"dealType":"중개거래"},{"contractYm":"202410","contractDay":"09","price":54800,"deposit":0,"monthlyRent":0,"area":59.9912,"areaPyeong":18.1,"floor":16,"dealType":"중개거래"},{"contractYm":"202410","contractDay":"03","price":57000,"deposit":0,"monthlyRent":0,"area":59.9912,"areaPyeong":18.1,"floor":19,"dealType":"중개거래"},{"contractYm":"202409","contractDay":"30","price":72000,"deposit":0,"monthlyRent":0,"area":84.52,"areaPyeong":25.6,"floor":19,"dealType":"중개거래"},{"contractYm":"202409","contractDay":"21","price":58000,"deposit":0,"monthlyRent":0,"area":59.9912,"areaPyeong":18.1,"floor":28,"dealType":"중개거래"},{"contractYm":"202409","contractDay":"13","price":54000,"deposit":0,"monthlyRent":0,"area":59.9912,"areaPyeong":18.1,"floor":16,"dealType":"중개거래"},{"contractYm":"202409","contractDay":"10","price":65000,"deposit":0,"monthlyRent":0,"area":84.52,"areaPyeong":25.6,"floor":19,"dealType":"중개거래"},{"contractYm":"202409","contractDay":"06","price":58700,"deposit":0,"monthlyRent":0,"area":60.3768,"areaPyeong":18.3,"floor":13,"dealType":"중개거래"},{"contractYm":"202409","contractDay":"06","price":59500,"deposit":0,"monthlyRent":0,"area":59.9912,"areaPyeong":18.1,"floor":18,"dealType":"중개거래"},{"contractYm":"202408","contractDay":"29","price":57000,"deposit":0,"monthlyRent":0,"area":59.9912,"areaPyeong":18.1,"floor":11,"dealType":"중개거래"},{"contractYm":"202408","contractDay":"21","price":55000,"deposit":0,"monthlyRent":0,"area":59.9912,"areaPyeong":18.1,"floor":4,"dealType":"중개거래"},{"contractYm":"202408","contractDay":"02","price":56000,"deposit":0,"monthlyRent":0,"area":60.3768,"areaPyeong":18.3,"floor":6,"dealType":"중개거래"},{"contractYm":"202408","contractDay":"01","price":56000,"deposit":0,"monthlyRent":0,"area":59.9912,"areaPyeong":18.1,"floor":9,"dealType":"중개거래"},{"contractYm":"202407","contractDay":"28","price":72800,"deposit":0,"monthlyRent":0,"area":84.5413,"areaPyeong":25.6,"floor":25,"dealType":"중개거래"},{"contractYm":"202407","contractDay":"13","price":55000,"deposit":0,"monthlyRent":0,"area":59.9912,"areaPyeong":18.1,"floor":10,"dealType":"중개거래"},{"contractYm":"202407","contractDay":"11","price":66000,"deposit":0,"monthlyRent":0,"area":84.5413,"areaPyeong":25.6,"floor":1,"dealType":"중개거래"},{"contractYm":"202406","contractDay":"25","price":50000,"deposit":0,"monthlyRent":0,"area":59.9912,"areaPyeong":18.1,"floor":20,"dealType":"중개거래"},{"contractYm":"202406","contractDay":"24","price":54000,"deposit":0,"monthlyRent":0,"area":60.3768,"areaPyeong":18.3,"floor":5,"dealType":"중개거래"},{"contractYm":"202406","contractDay":"15","price":55800,"deposit":0,"monthlyRent":0,"area":59.9912,"areaPyeong":18.1,"floor":16,"dealType":"중개거래"},{"contractYm":"202405","contractDay":"04","price":55900,"deposit":0,"monthlyRent":0,"area":59.9912,"areaPyeong":18.1,"floor":17,"dealType":"중개거래"},{"contractYm":"202405","contractDay":"03","price":51000,"deposit":0,"monthlyRent":0,"area":59.9912,"areaPyeong":18.1,"floor":14,"dealType":"중개거래"},{"contractYm":"202404","contractDay":"20","price":72000,"deposit":0,"monthlyRent":0,"area":84.52,"areaPyeong":25.6,"floor":11,"dealType":"중개거래"},{"contractYm":"202404","contractDay":"10","price":72500,"deposit":0,"monthlyRent":0,"area":84.52,"areaPyeong":25.6,"floor":17,"dealType":"중개거래"},{"contractYm":"202403","contractDay":"30","price":53000,"deposit":0,"monthlyRent":0,"area":59.9912,"areaPyeong":18.1,"floor":6,"dealType":"중개거래"},{"contractYm":"202402","contractDay":"27","price":55700,"deposit":0,"monthlyRent":0,"area":59.9912,"areaPyeong":18.1,"floor":12,"dealType":"중개거래"},{"contractYm":"202402","contractDay":"22","price":56000,"deposit":0,"monthlyRent":0,"area":60.3768,"areaPyeong":18.3,"floor":7,"dealType":"중개거래"},{"contractYm":"202402","contractDay":"21","price":53000,"deposit":0,"monthlyRent":0,"area":60.3768,"areaPyeong":18.3,"floor":4,"dealType":"중개거래"},{"contractYm":"202401","contractDay":"26","price":56000,"deposit":0,"monthlyRent":0,"area":60.3768,"areaPyeong":18.3,"floor":14,"dealType":"중개거래"},{"contractYm":"202401","contractDay":"19","price":42000,"deposit":0,"monthlyRent":0,"area":60.3768,"areaPyeong":18.3,"floor":2,"dealType":"직거래"},{"contractYm":"202312","contractDay":"09","price":52800,"deposit":0,"monthlyRent":0,"area":60.3768,"areaPyeong":18.3,"floor":2,"dealType":"중개거래"},{"contractYm":"202311","contractDay":"24","price":58000,"deposit":0,"monthlyRent":0,"area":59.9912,"areaPyeong":18.1,"floor":15,"dealType":"중개거래"},{"contractYm":"202311","contractDay":"11","price":55500,"deposit":0,"monthlyRent":0,"area":60.3768,"areaPyeong":18.3,"floor":5,"dealType":"중개거래"},{"contractYm":"202311","contractDay":"10","price":53700,"deposit":0,"monthlyRent":0,"area":59.9912,"areaPyeong":18.1,"floor":3,"dealType":"중개거래"},{"contractYm":"202311","contractDay":"03","price":52400,"deposit":0,"monthlyRent":0,"area":59.9912,"areaPyeong":18.1,"floor":2,"dealType":"중개거래"},{"contractYm":"202310","contractDay":"13","price":58000,"deposit":0,"monthlyRent":0,"area":60.3768,"areaPyeong":18.3,"floor":15,"dealType":"중개거래"},{"contractYm":"202310","contractDay":"10","price":55000,"deposit":0,"monthlyRent":0,"area":59.9912,"areaPyeong":18.1,"floor":11,"dealType":"중개거래"},{"contractYm":"202309","contractDay":"21","price":53800,"deposit":0,"monthlyRent":0,"area":59.9912,"areaPyeong":18.1,"floor":5,"dealType":"중개거래"},{"contractYm":"202309","contractDay":"18","price":73500,"deposit":0,"monthlyRent":0,"area":84.52,"areaPyeong":25.6,"floor":1,"dealType":"중개거래"},{"contractYm":"202309","contractDay":"08","price":58000,"deposit":0,"monthlyRent":0,"area":59.9912,"areaPyeong":18.1,"floor":25,"dealType":"중개거래"},{"contractYm":"202309","contractDay":"04","price":55000,"deposit":0,"monthlyRent":0,"area":59.9912,"areaPyeong":18.1,"floor":22,"dealType":"중개거래"},{"contractYm":"202308","contractDay":"31","price":49900,"deposit":0,"monthlyRent":0,"area":59.9912,"areaPyeong":18.1,"floor":1,"dealType":"중개거래"},{"contractYm":"202308","contractDay":"28","price":51700,"deposit":0,"monthlyRent":0,"area":59.9912,"areaPyeong":18.1,"floor":2,"dealType":"중개거래"},{"contractYm":"202308","contractDay":"23","price":57000,"deposit":0,"monthlyRent":0,"area":59.9912,"areaPyeong":18.1,"floor":16,"dealType":"중개거래"},{"contractYm":"202308","contractDay":"19","price":52800,"deposit":0,"monthlyRent":0,"area":59.9912,"areaPyeong":18.1,"floor":3,"dealType":"중개거래"},{"contractYm":"202307","contractDay":"29","price":73500,"deposit":0,"monthlyRent":0,"area":84.52,"areaPyeong":25.6,"floor":17,"dealType":"중개거래"},{"contractYm":"202307","contractDay":"28","price":57500,"deposit":0,"monthlyRent":0,"area":59.9912,"areaPyeong":18.1,"floor":16,"dealType":"중개거래"},{"contractYm":"202307","contractDay":"27","price":56000,"deposit":0,"monthlyRent":0,"area":59.9912,"areaPyeong":18.1,"floor":22,"dealType":"중개거래"},{"contractYm":"202307","contractDay":"18","price":53000,"deposit":0,"monthlyRent":0,"area":59.9912,"areaPyeong":18.1,"floor":13,"dealType":"중개거래"},{"contractYm":"202307","contractDay":"15","price":50000,"deposit":0,"monthlyRent":0,"area":59.9912,"areaPyeong":18.1,"floor":10,"dealType":"직거래"},{"contractYm":"202306","contractDay":"26","price":47900,"deposit":0,"monthlyRent":0,"area":59.9912,"areaPyeong":18.1,"floor":2,"dealType":"중개거래"},{"contractYm":"202306","contractDay":"14","price":53800,"deposit":0,"monthlyRent":0,"area":60.3768,"areaPyeong":18.3,"floor":7,"dealType":"중개거래"},{"contractYm":"202306","contractDay":"03","price":53500,"deposit":0,"monthlyRent":0,"area":59.9912,"areaPyeong":18.1,"floor":8,"dealType":"중개거래"},{"contractYm":"202305","contractDay":"27","price":52500,"deposit":0,"monthlyRent":0,"area":59.9912,"areaPyeong":18.1,"floor":5,"dealType":"중개거래"},{"contractYm":"202305","contractDay":"23","price":54900,"deposit":0,"monthlyRent":0,"area":60.3768,"areaPyeong":18.3,"floor":12,"dealType":"중개거래"},{"contractYm":"202305","contractDay":"22","price":77000,"deposit":0,"monthlyRent":0,"area":84.52,"areaPyeong":25.6,"floor":10,"dealType":"중개거래"},{"contractYm":"202305","contractDay":"22","price":53800,"deposit":0,"monthlyRent":0,"area":59.9912,"areaPyeong":18.1,"floor":23,"dealType":"중개거래"},{"contractYm":"202305","contractDay":"20","price":54000,"deposit":0,"monthlyRent":0,"area":59.9912,"areaPyeong":18.1,"floor":23,"dealType":"중개거래"},{"contractYm":"202305","contractDay":"17","price":53000,"deposit":0,"monthlyRent":0,"area":59.9912,"areaPyeong":18.1,"floor":24,"dealType":"중개거래"},{"contractYm":"202305","contractDay":"13","price":52900,"deposit":0,"monthlyRent":0,"area":59.9912,"areaPyeong":18.1,"floor":10,"dealType":"중개거래"},{"contractYm":"202305","contractDay":"12","price":51500,"deposit":0,"monthlyRent":0,"area":60.3768,"areaPyeong":18.3,"floor":6,"dealType":"중개거래"},{"contractYm":"202305","contractDay":"04","price":52000,"deposit":0,"monthlyRent":0,"area":59.9912,"areaPyeong":18.1,"floor":20,"dealType":"중개거래"},{"contractYm":"202304","contractDay":"23","price":50500,"deposit":0,"monthlyRent":0,"area":59.9912,"areaPyeong":18.1,"floor":16,"dealType":"중개거래"},{"contractYm":"202304","contractDay":"20","price":49700,"deposit":0,"monthlyRent":0,"area":59.9912,"areaPyeong":18.1,"floor":1,"dealType":"중개거래"},{"contractYm":"202304","contractDay":"19","price":51000,"deposit":0,"monthlyRent":0,"area":59.9912,"areaPyeong":18.1,"floor":14,"dealType":"중개거래"},{"contractYm":"202303","contractDay":"31","price":68000,"deposit":0,"monthlyRent":0,"area":84.52,"areaPyeong":25.6,"floor":6,"dealType":"중개거래"},{"contractYm":"202303","contractDay":"31","price":49800,"deposit":0,"monthlyRent":0,"area":59.9912,"areaPyeong":18.1,"floor":12,"dealType":"중개거래"},{"contractYm":"202303","contractDay":"18","price":67000,"deposit":0,"monthlyRent":0,"area":84.5413,"areaPyeong":25.6,"floor":27,"dealType":"중개거래"},{"contractYm":"202303","contractDay":"16","price":52500,"deposit":0,"monthlyRent":0,"area":60.3768,"areaPyeong":18.3,"floor":11,"dealType":"중개거래"},{"contractYm":"202303","contractDay":"16","price":49700,"deposit":0,"monthlyRent":0,"area":59.9912,"areaPyeong":18.1,"floor":26,"dealType":"중개거래"},{"contractYm":"202303","contractDay":"15","price":59500,"deposit":0,"monthlyRent":0,"area":84.5442,"areaPyeong":25.6,"floor":1,"dealType":"중개거래"},{"contractYm":"202303","contractDay":"04","price":67000,"deposit":0,"monthlyRent":0,"area":84.5413,"areaPyeong":25.6,"floor":27,"dealType":"중개거래"},{"contractYm":"202303","contractDay":"04","price":49000,"deposit":0,"monthlyRent":0,"area":59.9912,"areaPyeong":18.1,"floor":11,"dealType":"중개거래"},{"contractYm":"202302","contractDay":"21","price":48000,"deposit":0,"monthlyRent":0,"area":60.3768,"areaPyeong":18.3,"floor":10,"dealType":"중개거래"},{"contractYm":"202302","contractDay":"21","price":47800,"deposit":0,"monthlyRent":0,"area":60.3768,"areaPyeong":18.3,"floor":3,"dealType":"중개거래"},{"contractYm":"202302","contractDay":"20","price":44500,"deposit":0,"monthlyRent":0,"area":60.3768,"areaPyeong":18.3,"floor":1,"dealType":"중개거래"},{"contractYm":"202302","contractDay":"15","price":62500,"deposit":0,"monthlyRent":0,"area":84.52,"areaPyeong":25.6,"floor":12,"dealType":"중개거래"},{"contractYm":"202302","contractDay":"11","price":47000,"deposit":0,"monthlyRent":0,"area":60.3768,"areaPyeong":18.3,"floor":3,"dealType":"중개거래"},{"contractYm":"202301","contractDay":"18","price":59800,"deposit":0,"monthlyRent":0,"area":84.5413,"areaPyeong":25.6,"floor":8,"dealType":"중개거래"},{"contractYm":"202212","contractDay":"06","price":45000,"deposit":0,"monthlyRent":0,"area":59.9912,"areaPyeong":18.1,"floor":12,"dealType":"중개거래"},{"contractYm":"202211","contractDay":"30","price":45000,"deposit":0,"monthlyRent":0,"area":59.9912,"areaPyeong":18.1,"floor":18,"dealType":"중개거래"},{"contractYm":"202211","contractDay":"23","price":40500,"deposit":0,"monthlyRent":0,"area":60.3768,"areaPyeong":18.3,"floor":4,"dealType":"중개거래"},{"contractYm":"202211","contractDay":"18","price":45000,"deposit":0,"monthlyRent":0,"area":59.9912,"areaPyeong":18.1,"floor":20,"dealType":"중개거래"},{"contractYm":"202210","contractDay":"25","price":40000,"deposit":0,"monthlyRent":0,"area":59.9912,"areaPyeong":18.1,"floor":13,"dealType":"중개거래"},{"contractYm":"202210","contractDay":"17","price":65500,"deposit":0,"monthlyRent":0,"area":84.5442,"areaPyeong":25.6,"floor":16,"dealType":"중개거래"},{"contractYm":"202210","contractDay":"03","price":67000,"deposit":0,"monthlyRent":0,"area":84.5442,"areaPyeong":25.6,"floor":13,"dealType":"중개거래"},{"contractYm":"202210","contractDay":"01","price":67000,"deposit":0,"monthlyRent":0,"area":84.5442,"areaPyeong":25.6,"floor":13,"dealType":"중개거래"},{"contractYm":"202209","contractDay":"26","price":43000,"deposit":0,"monthlyRent":0,"area":59.9912,"areaPyeong":18.1,"floor":2,"dealType":"중개거래"},{"contractYm":"202209","contractDay":"20","price":45000,"deposit":0,"monthlyRent":0,"area":59.9912,"areaPyeong":18.1,"floor":19,"dealType":"중개거래"},{"contractYm":"202208","contractDay":"25","price":70000,"deposit":0,"monthlyRent":0,"area":84.52,"areaPyeong":25.6,"floor":20,"dealType":"중개거래"},{"contractYm":"202208","contractDay":"20","price":75000,"deposit":0,"monthlyRent":0,"area":84.5413,"areaPyeong":25.6,"floor":7,"dealType":"직거래"},{"contractYm":"202208","contractDay":"11","price":60000,"deposit":0,"monthlyRent":0,"area":59.9912,"areaPyeong":18.1,"floor":20,"dealType":"직거래"},{"contractYm":"202208","contractDay":"01","price":59700,"deposit":0,"monthlyRent":0,"area":59.9912,"areaPyeong":18.1,"floor":19,"dealType":"중개거래"},{"contractYm":"202207","contractDay":"17","price":57000,"deposit":0,"monthlyRent":0,"area":59.9912,"areaPyeong":18.1,"floor":8,"dealType":"중개거래"},{"contractYm":"202206","contractDay":"09","price":59000,"deposit":0,"monthlyRent":0,"area":60.3768,"areaPyeong":18.3,"floor":5,"dealType":"중개거래"},{"contractYm":"202204","contractDay":"17","price":64000,"deposit":0,"monthlyRent":0,"area":60.3768,"areaPyeong":18.3,"floor":7,"dealType":"중개거래"},{"contractYm":"202203","contractDay":"18","price":65000,"deposit":0,"monthlyRent":0,"area":59.9912,"areaPyeong":18.1,"floor":17,"dealType":"중개거래"},{"contractYm":"202203","contractDay":"06","price":62300,"deposit":0,"monthlyRent":0,"area":59.9912,"areaPyeong":18.1,"floor":14,"dealType":"중개거래"},{"contractYm":"202201","contractDay":"29","price":60000,"deposit":0,"monthlyRent":0,"area":59.9912,"areaPyeong":18.1,"floor":13,"dealType":"중개거래"},{"contractYm":"202201","contractDay":"25","price":59000,"deposit":0,"monthlyRent":0,"area":59.9912,"areaPyeong":18.1,"floor":6,"dealType":"중개거래"},{"contractYm":"202201","contractDay":"15","price":63500,"deposit":0,"monthlyRent":0,"area":59.9912,"areaPyeong":18.1,"floor":18,"dealType":"중개거래"},{"contractYm":"202111","contractDay":"26","price":65700,"deposit":0,"monthlyRent":0,"area":60.3768,"areaPyeong":18.3,"floor":5,"dealType":"중개거래"},{"contractYm":"202110","contractDay":"26","price":70000,"deposit":0,"monthlyRent":0,"area":59.9912,"areaPyeong":18.1,"floor":11,"dealType":"-"},{"contractYm":"202110","contractDay":"22","price":93500,"deposit":0,"monthlyRent":0,"area":84.5442,"areaPyeong":25.6,"floor":8,"dealType":"-"},{"contractYm":"202110","contractDay":"16","price":94800,"deposit":0,"monthlyRent":0,"area":84.52,"areaPyeong":25.6,"floor":10,"dealType":"-"},{"contractYm":"202109","contractDay":"17","price":92500,"deposit":0,"monthlyRent":0,"area":84.5413,"areaPyeong":25.6,"floor":21,"dealType":"-"},{"contractYm":"202109","contractDay":"10","price":64300,"deposit":0,"monthlyRent":0,"area":59.9912,"areaPyeong":18.1,"floor":5,"dealType":"-"},{"contractYm":"202108","contractDay":"24","price":84800,"deposit":0,"monthlyRent":0,"area":84.52,"areaPyeong":25.6,"floor":3,"dealType":"-"},{"contractYm":"202108","contractDay":"21","price":73700,"deposit":0,"monthlyRent":0,"area":60.3768,"areaPyeong":18.3,"floor":14,"dealType":"-"},{"contractYm":"202108","contractDay":"16","price":70000,"deposit":0,"monthlyRent":0,"area":59.9912,"areaPyeong":18.1,"floor":8,"dealType":"-"},{"contractYm":"202108","contractDay":"16","price":70000,"deposit":0,"monthlyRent":0,"area":59.9912,"areaPyeong":18.1,"floor":5,"dealType":"-"},{"contractYm":"202108","contractDay":"07","price":69000,"deposit":0,"monthlyRent":0,"area":60.3768,"areaPyeong":18.3,"floor":6,"dealType":"-"},{"contractYm":"202107","contractDay":"30","price":82000,"deposit":0,"monthlyRent":0,"area":84.5413,"areaPyeong":25.6,"floor":3,"dealType":"-"},{"contractYm":"202107","contractDay":"30","price":63000,"deposit":0,"monthlyRent":0,"area":59.9912,"areaPyeong":18.1,"floor":14,"dealType":"-"},{"contractYm":"202107","contractDay":"29","price":70000,"deposit":0,"monthlyRent":0,"area":59.9912,"areaPyeong":18.1,"floor":22,"dealType":"-"},{"contractYm":"202107","contractDay":"28","price":65500,"deposit":0,"monthlyRent":0,"area":60.3768,"areaPyeong":18.3,"floor":10,"dealType":"-"},{"contractYm":"202107","contractDay":"27","price":64000,"deposit":0,"monthlyRent":0,"area":60.3768,"areaPyeong":18.3,"floor":14,"dealType":"-"},{"contractYm":"202107","contractDay":"26","price":65900,"deposit":0,"monthlyRent":0,"area":59.9912,"areaPyeong":18.1,"floor":9,"dealType":"-"},{"contractYm":"202107","contractDay":"24","price":62900,"deposit":0,"monthlyRent":0,"area":59.9912,"areaPyeong":18.1,"floor":5,"dealType":"-"},{"contractYm":"202107","contractDay":"20","price":62000,"deposit":0,"monthlyRent":0,"area":59.9912,"areaPyeong":18.1,"floor":26,"dealType":"-"},{"contractYm":"202107","contractDay":"19","price":62250,"deposit":0,"monthlyRent":0,"area":59.9912,"areaPyeong":18.1,"floor":12,"dealType":"-"},{"contractYm":"202107","contractDay":"18","price":59900,"deposit":0,"monthlyRent":0,"area":59.9912,"areaPyeong":18.1,"floor":7,"dealType":"-"},{"contractYm":"202107","contractDay":"17","price":83000,"deposit":0,"monthlyRent":0,"area":84.5442,"areaPyeong":25.6,"floor":3,"dealType":"-"},{"contractYm":"202107","contractDay":"15","price":63000,"deposit":0,"monthlyRent":0,"area":59.9912,"areaPyeong":18.1,"floor":21,"dealType":"-"},{"contractYm":"202107","contractDay":"14","price":59900,"deposit":0,"monthlyRent":0,"area":59.9912,"areaPyeong":18.1,"floor":4,"dealType":"-"},{"contractYm":"202107","contractDay":"07","price":60000,"deposit":0,"monthlyRent":0,"area":60.3768,"areaPyeong":18.3,"floor":8,"dealType":"-"},{"contractYm":"202107","contractDay":"03","price":61500,"deposit":0,"monthlyRent":0,"area":60.3768,"areaPyeong":18.3,"floor":8,"dealType":"-"},{"contractYm":"202107","contractDay":"01","price":60000,"deposit":0,"monthlyRent":0,"area":59.9912,"areaPyeong":18.1,"floor":7,"dealType":"-"},{"contractYm":"202106","contractDay":"29","price":55500,"deposit":0,"monthlyRent":0,"area":59.9912,"areaPyeong":18.1,"floor":1,"dealType":"-"},{"contractYm":"202106","contractDay":"28","price":60000,"deposit":0,"monthlyRent":0,"area":59.9912,"areaPyeong":18.1,"floor":8,"dealType":"-"},{"contractYm":"202106","contractDay":"26","price":59300,"deposit":0,"monthlyRent":0,"area":59.9912,"areaPyeong":18.1,"floor":6,"dealType":"-"},{"contractYm":"202106","contractDay":"24","price":76500,"deposit":0,"monthlyRent":0,"area":84.52,"areaPyeong":25.6,"floor":2,"dealType":"-"},{"contractYm":"202106","contractDay":"24","price":55300,"deposit":0,"monthlyRent":0,"area":60.3768,"areaPyeong":18.3,"floor":1,"dealType":"-"},{"contractYm":"202106","contractDay":"18","price":62000,"deposit":0,"monthlyRent":0,"area":59.9912,"areaPyeong":18.1,"floor":23,"dealType":"-"},{"contractYm":"202106","contractDay":"17","price":62000,"deposit":0,"monthlyRent":0,"area":59.9912,"areaPyeong":18.1,"floor":19,"dealType":"-"},{"contractYm":"202106","contractDay":"11","price":61000,"deposit":0,"monthlyRent":0,"area":59.9912,"areaPyeong":18.1,"floor":15,"dealType":"-"},{"contractYm":"202106","contractDay":"10","price":81200,"deposit":0,"monthlyRent":0,"area":84.5413,"areaPyeong":25.6,"floor":12,"dealType":"-"},{"contractYm":"202106","contractDay":"08","price":59900,"deposit":0,"monthlyRent":0,"area":60.3768,"areaPyeong":18.3,"floor":10,"dealType":"-"},{"contractYm":"202105","contractDay":"22","price":59800,"deposit":0,"monthlyRent":0,"area":59.9912,"areaPyeong":18.1,"floor":23,"dealType":"-"},{"contractYm":"202105","contractDay":"22","price":59000,"deposit":0,"monthlyRent":0,"area":59.9912,"areaPyeong":18.1,"floor":16,"dealType":"-"},{"contractYm":"202105","contractDay":"14","price":57800,"deposit":0,"monthlyRent":0,"area":60.3768,"areaPyeong":18.3,"floor":9,"dealType":"-"},{"contractYm":"202105","contractDay":"07","price":52500,"deposit":0,"monthlyRent":0,"area":60.3768,"areaPyeong":18.3,"floor":1,"dealType":"-"},{"contractYm":"202104","contractDay":"23","price":80700,"deposit":0,"monthlyRent":0,"area":84.52,"areaPyeong":25.6,"floor":26,"dealType":"-"},{"contractYm":"202104","contractDay":"07","price":58700,"deposit":0,"monthlyRent":0,"area":60.3768,"areaPyeong":18.3,"floor":5,"dealType":"-"},{"contractYm":"202103","contractDay":"24","price":59500,"deposit":0,"monthlyRent":0,"area":60.3768,"areaPyeong":18.3,"floor":13,"dealType":"-"},{"contractYm":"202103","contractDay":"19","price":58000,"deposit":0,"monthlyRent":0,"area":59.9912,"areaPyeong":18.1,"floor":9,"dealType":"-"},{"contractYm":"202103","contractDay":"18","price":59900,"deposit":0,"monthlyRent":0,"area":60.3768,"areaPyeong":18.3,"floor":14,"dealType":"-"},{"contractYm":"202103","contractDay":"18","price":59500,"deposit":0,"monthlyRent":0,"area":59.9912,"areaPyeong":18.1,"floor":18,"dealType":"-"},{"contractYm":"202103","contractDay":"16","price":61000,"deposit":0,"monthlyRent":0,"area":59.9912,"areaPyeong":18.1,"floor":24,"dealType":"-"},{"contractYm":"202103","contractDay":"08","price":52000,"deposit":0,"monthlyRent":0,"area":59.9912,"areaPyeong":18.1,"floor":1,"dealType":"-"},{"contractYm":"202103","contractDay":"06","price":54000,"deposit":0,"monthlyRent":0,"area":59.9912,"areaPyeong":18.1,"floor":12,"dealType":"-"},{"contractYm":"202102","contractDay":"10","price":59300,"deposit":0,"monthlyRent":0,"area":59.9912,"areaPyeong":18.1,"floor":20,"dealType":"-"},{"contractYm":"202102","contractDay":"08","price":60000,"deposit":0,"monthlyRent":0,"area":59.9912,"areaPyeong":18.1,"floor":19,"dealType":"-"},{"contractYm":"202101","contractDay":"29","price":58000,"deposit":0,"monthlyRent":0,"area":59.9912,"areaPyeong":18.1,"floor":8,"dealType":"-"},{"contractYm":"202101","contractDay":"04","price":80000,"deposit":0,"monthlyRent":0,"area":84.52,"areaPyeong":25.6,"floor":26,"dealType":"-"},{"contractYm":"202012","contractDay":"11","price":78000,"deposit":0,"monthlyRent":0,"area":84.52,"areaPyeong":25.6,"floor":22,"dealType":"-"},{"contractYm":"202011","contractDay":"30","price":77600,"deposit":0,"monthlyRent":0,"area":84.52,"areaPyeong":25.6,"floor":22,"dealType":"-"},{"contractYm":"202011","contractDay":"28","price":75500,"deposit":0,"monthlyRent":0,"area":84.5442,"areaPyeong":25.6,"floor":11,"dealType":"-"},{"contractYm":"202011","contractDay":"27","price":76500,"deposit":0,"monthlyRent":0,"area":84.5442,"areaPyeong":25.6,"floor":15,"dealType":"-"},{"contractYm":"202010","contractDay":"17","price":54500,"deposit":0,"monthlyRent":0,"area":59.9912,"areaPyeong":18.1,"floor":4,"dealType":"-"},{"contractYm":"202009","contractDay":"12","price":53000,"deposit":0,"monthlyRent":0,"area":59.9912,"areaPyeong":18.1,"floor":20,"dealType":"-"},{"contractYm":"202009","contractDay":"09","price":74000,"deposit":0,"monthlyRent":0,"area":84.52,"areaPyeong":25.6,"floor":5,"dealType":"-"},{"contractYm":"202007","contractDay":"06","price":51000,"deposit":0,"monthlyRent":0,"area":59.9912,"areaPyeong":18.1,"floor":4,"dealType":"-"},{"contractYm":"202001","contractDay":"29","price":35000,"deposit":0,"monthlyRent":0,"area":59.9912,"areaPyeong":18.1,"floor":19,"dealType":"-"},{"contractYm":"202001","contractDay":"17","price":59500,"deposit":0,"monthlyRent":0,"area":84.52,"areaPyeong":25.6,"floor":16,"dealType":"-"},{"contractYm":"201912","contractDay":"18","price":44500,"deposit":0,"monthlyRent":0,"area":59.9912,"areaPyeong":18.1,"floor":11,"dealType":"-"},{"contractYm":"201912","contractDay":"04","price":30200,"deposit":0,"monthlyRent":0,"area":59.9912,"areaPyeong":18.1,"floor":15,"dealType":"-"},{"contractYm":"201910","contractDay":"24","price":36700,"deposit":0,"monthlyRent":0,"area":59.9912,"areaPyeong":18.1,"floor":6,"dealType":"-"},{"contractYm":"201910","contractDay":"09","price":50000,"deposit":0,"monthlyRent":0,"area":84.5413,"areaPyeong":25.6,"floor":6,"dealType":"-"},{"contractYm":"201910","contractDay":"02","price":50000,"deposit":0,"monthlyRent":0,"area":84.5413,"areaPyeong":25.6,"floor":25,"dealType":"-"},{"contractYm":"201909","contractDay":"01","price":30400,"deposit":0,"monthlyRent":0,"area":59.9912,"areaPyeong":18.1,"floor":2,"dealType":"-"},{"contractYm":"201907","contractDay":"24","price":32000,"deposit":0,"monthlyRent":0,"area":60.3768,"areaPyeong":18.3,"floor":4,"dealType":"-"},{"contractYm":"201906","contractDay":"19","price":33000,"deposit":0,"monthlyRent":0,"area":59.9912,"areaPyeong":18.1,"floor":3,"dealType":"-"},{"contractYm":"201905","contractDay":"03","price":42300,"deposit":0,"monthlyRent":0,"area":84.5413,"areaPyeong":25.6,"floor":3,"dealType":"-"},{"contractYm":"201902","contractDay":"13","price":32500,"deposit":0,"monthlyRent":0,"area":59.9912,"areaPyeong":18.1,"floor":9,"dealType":"-"}]